Metadata-Version: 1.0
Name: sid-dsnd
Version: 0.1
Summary: Gaussian distributions
Home-page: UNKNOWN
Author: Sidharth S
Author-email: sidharths758@gmail.com
License: UNKNOWN
Platform: UNKNOWN
